{"_type":"export","__export_format":4,"__export_date":"2022-10-14T20:27:26.792Z","__export_source":"insomnia.desktop.app:v2022.6.0","resources":[{"_id":"req_8ae9c9969d2b4953995125d917ab8658","parentId":"fld_ad01f914a8c24487a866eb3f188f64de","modified":1665779056842,"created":1665778985072,"url":"{{ _.baseURL }}/client/","name":"Create","description":"","method":"POST","body":{"mimeType":"application/json","text":"{\n\t\"username\":\"JeffyMesquita\",\n\t\"password\":\"12345678\"\n}"},"parameters":[],"headers":[{"name":"Content-Type","value":"application/json"}],"authentication":{},"metaSortKey":-1665778985072,"isPrivate":false,"settingStoreCookies":true,"settingSendCookies":true,"settingDisableRenderRequestBody":false,"settingEncodeUrl":true,"settingRebuildPath":true,"settingFollowRedirects":"global","_type":"request"},{"_id":"fld_ad01f914a8c24487a866eb3f188f64de","parentId":"wrk_e382eeeeae44448797a60edd34e4fda9","modified":1665778904218,"created":1665778904218,"name":"Clients","description":"","environment":{},"environmentPropertyOrder":null,"metaSortKey":-1665778904218,"_type":"request_group"},{"_id":"wrk_e382eeeeae44448797a60edd34e4fda9","parentId":null,"modified":1665778897797,"created":1665778897797,"name":"Backend-Entregas","description":"","scope":"collection","_type":"workspace"},{"_id":"env_6e3df6c1df9dfe5f90e7e4bfd99fff9c0f221cd5","parentId":"wrk_e382eeeeae44448797a60edd34e4fda9","modified":1665778963810,"created":1665778897803,"name":"Base Environment","data":{"baseURL":"http://localhost:3000"},"dataPropertyOrder":{"&":["baseURL"]},"color":null,"isPrivate":false,"metaSortKey":1665778897803,"_type":"environment"},{"_id":"jar_6e3df6c1df9dfe5f90e7e4bfd99fff9c0f221cd5","parentId":"wrk_e382eeeeae44448797a60edd34e4fda9","modified":1665778897805,"created":1665778897805,"name":"Default Jar","cookies":[],"_type":"cookie_jar"},{"_id":"spc_8cc5206f34114303a79aeb9b598b452d","parentId":"wrk_e382eeeeae44448797a60edd34e4fda9","modified":1665778897798,"created":1665778897798,"fileName":"Backend-Entregas","contents":"","contentType":"yaml","_type":"api_spec"}]}